whitehouse/__init__.py
whitehouse/base.py
whitehouse/custom.py
whitehouse/default.py
whitehouse/utils.py
whitehouse-0.3.1.dist-info/METADATA
whitehouse-0.3.1.dist-info/WHEEL
whitehouse-0.3.1.dist-info/top_level.txt
whitehouse-0.3.1.dist-info/RECORD
