Metadata-Version: 2.1
Name: whitehouse
Version: 0.3.1
Summary: An html templating library for Python
Author: Minh-Quan Do
Author-email: mdo9@gmu.edu
Requires-Dist: beautifulsoup4
